README.md
setup.cfg
setup.py
bin/main.py
gitlab_group_project_exporter.egg-info/PKG-INFO
gitlab_group_project_exporter.egg-info/SOURCES.txt
gitlab_group_project_exporter.egg-info/dependency_links.txt
gitlab_group_project_exporter.egg-info/requires.txt
gitlab_group_project_exporter.egg-info/top_level.txt
gitlabexporter/__init__.py
gitlabexporter/groupexport.py
gitlabexporter/projectexport.py