Metadata-Version: 1.1
Name: gitlab-group-project-exporter
Version: 1.0.4
Summary: Export gitlab groups and projects for remote backups
Home-page: https://github.com/masad8
Author: Muhammad Asad
Author-email: muhammad.asad@gmail.com
License: MIT
Keywords: Gitlab,Exporter,Backup
Platform: UNKNOWN
Classifier: License :: OSI Approved :: MIT License
Classifier: Programming Language :: Python :: 3
Classifier: Programming Language :: Python :: 3.8
